{
	"id": "150000",
	"key": "TIMOB-19286",
	"fields": {
		"issuetype": {
			"id": "7",
			"description": "gh.issue.story.desc",
			"name": "Story",
			"subtask": false
		},
		"project": {
			"id": "10153",
			"key": "TIMOB",
			"name": "Titanium SDK/CLI",
			"projectCategory": {
				"id": "10100",
				"description": "Titanium and related SDKs used in application development",
				"name": "Client"
			}
		},
		"fixVersions": [],
		"resolution": {
			"id": "1",
			"description": "A fix for this issue is checked into the tree and tested.",
			"name": "Fixed"
		},
		"resolutiondate": "2015-09-09T16:32:47.000+0000",
		"created": "2015-07-29T23:21:53.000+0000",
		"priority": {
			"name": "Medium",
			"id": "3"
		},
		"labels": [],
		"versions": [],
		"issuelinks": [
			{
				"id": "48772",
				"type": {
					"id": "10000",
					"name": "Blocks",
					"inward": "is blocked by",
					"outward": "blocks"
				},
				"inwardIssue": {
					"id": "150643",
					"key": "TIMOB-19399",
					"fields": {
						"summary": "Windows: Missing functions for ScrollView TitaniumKit",
						"status": {
							"description": "The issue is considered finished, the resolution is correct. Issues which are closed can be reopened.",
							"name": "Closed",
							"id": "6",
							"statusCategory": {
								"id": 3,
								"key": "done",
								"colorName": "green",
								"name": "Done"
							}
						},
						"priority": {
							"name": "High",
							"id": "2"
						},
						"issuetype": {
							"id": "1",
							"description": "A problem which impairs or prevents the functions of the product.",
							"name": "Bug",
							"subtask": false
						}
					}
				}
			},
			{
				"id": "48774",
				"type": {
					"id": "10000",
					"name": "Blocks",
					"inward": "is blocked by",
					"outward": "blocks"
				},
				"inwardIssue": {
					"id": "150659",
					"key": "TIMOB-19401",
					"fields": {
						"summary": "Windows: Missing events for Ti.UI.View",
						"status": {
							"description": "The issue is considered finished, the resolution is correct. Issues which are closed can be reopened.",
							"name": "Closed",
							"id": "6",
							"statusCategory": {
								"id": 3,
								"key": "done",
								"colorName": "green",
								"name": "Done"
							}
						},
						"priority": {
							"name": "High",
							"id": "2"
						},
						"issuetype": {
							"id": "1",
							"description": "A problem which impairs or prevents the functions of the product.",
							"name": "Bug",
							"subtask": false
						}
					}
				}
			},
			{
				"id": "48849",
				"type": {
					"id": "10000",
					"name": "Blocks",
					"inward": "is blocked by",
					"outward": "blocks"
				},
				"inwardIssue": {
					"id": "150865",
					"key": "TIMOB-19442",
					"fields": {
						"summary": "Windows: ti build failed when logo image assets with invalid dimension exits",
						"status": {
							"description": "The issue is considered finished, the resolution is correct. Issues which are closed can be reopened.",
							"name": "Closed",
							"id": "6",
							"statusCategory": {
								"id": 3,
								"key": "done",
								"colorName": "green",
								"name": "Done"
							}
						},
						"priority": {
							"name": "Medium",
							"id": "3"
						},
						"issuetype": {
							"id": "1",
							"description": "A problem which impairs or prevents the functions of the product.",
							"name": "Bug",
							"subtask": false
						}
					}
				}
			},
			{
				"id": "48502",
				"type": {
					"id": "10001",
					"name": "Cloners",
					"inward": "is cloned into",
					"outward": "is cloned from"
				},
				"outwardIssue": {
					"id": "149019",
					"key": "TIMOB-19058",
					"fields": {
						"summary": "Windows: Test Field Service sample",
						"status": {
							"description": "The issue is considered finished, the resolution is correct. Issues which are closed can be reopened.",
							"name": "Closed",
							"id": "6",
							"statusCategory": {
								"id": 3,
								"key": "done",
								"colorName": "green",
								"name": "Done"
							}
						},
						"priority": {
							"name": "Medium",
							"id": "3"
						},
						"issuetype": {
							"id": "7",
							"description": "gh.issue.story.desc",
							"name": "Story",
							"subtask": false
						}
					}
				}
			},
			{
				"id": "48786",
				"type": {
					"id": "10003",
					"name": "Relates",
					"inward": "relates to",
					"outward": "relates to"
				},
				"outwardIssue": {
					"id": "150707",
					"key": "TIMOB-19409",
					"fields": {
						"summary": "Windows: Layout parity: View should \"crop\" child view",
						"status": {
							"description": "The issue is considered finished, the resolution is correct. Issues which are closed can be reopened.",
							"name": "Closed",
							"id": "6",
							"statusCategory": {
								"id": 3,
								"key": "done",
								"colorName": "green",
								"name": "Done"
							}
						},
						"priority": {
							"name": "High",
							"id": "2"
						},
						"issuetype": {
							"id": "1",
							"description": "A problem which impairs or prevents the functions of the product.",
							"name": "Bug",
							"subtask": false
						}
					}
				}
			},
			{
				"id": "48776",
				"type": {
					"id": "10003",
					"name": "Relates",
					"inward": "relates to",
					"outward": "relates to"
				},
				"outwardIssue": {
					"id": "150674",
					"key": "TIMOB-19404",
					"fields": {
						"summary": "Windows: ImageView Layout parity",
						"status": {
							"description": "The issue is considered finished, the resolution is correct. Issues which are closed can be reopened.",
							"name": "Closed",
							"id": "6",
							"statusCategory": {
								"id": 3,
								"key": "done",
								"colorName": "green",
								"name": "Done"
							}
						},
						"priority": {
							"name": "Medium",
							"id": "3"
						},
						"issuetype": {
							"id": "1",
							"description": "A problem which impairs or prevents the functions of the product.",
							"name": "Bug",
							"subtask": false
						}
					}
				}
			},
			{
				"id": "48835",
				"type": {
					"id": "10003",
					"name": "Relates",
					"inward": "relates to",
					"outward": "relates to"
				},
				"outwardIssue": {
					"id": "150841",
					"key": "TIMOB-19438",
					"fields": {
						"summary": "Windows: ScrollView contentOffset doesn't work",
						"status": {
							"description": "The issue is considered finished, the resolution is correct. Issues which are closed can be reopened.",
							"name": "Closed",
							"id": "6",
							"statusCategory": {
								"id": 3,
								"key": "done",
								"colorName": "green",
								"name": "Done"
							}
						},
						"priority": {
							"name": "Medium",
							"id": "3"
						},
						"issuetype": {
							"id": "1",
							"description": "A problem which impairs or prevents the functions of the product.",
							"name": "Bug",
							"subtask": false
						}
					}
				}
			},
			{
				"id": "48823",
				"type": {
					"id": "10003",
					"name": "Relates",
					"inward": "relates to",
					"outward": "relates to"
				},
				"outwardIssue": {
					"id": "150802",
					"key": "TIMOB-19426",
					"fields": {
						"summary": "Windows: animate doesn't work when duration is short",
						"status": {
							"description": "The issue is considered finished, the resolution is correct. Issues which are closed can be reopened.",
							"name": "Closed",
							"id": "6",
							"statusCategory": {
								"id": 3,
								"key": "done",
								"colorName": "green",
								"name": "Done"
							}
						},
						"priority": {
							"name": "None",
							"id": "6"
						},
						"issuetype": {
							"id": "1",
							"description": "A problem which impairs or prevents the functions of the product.",
							"name": "Bug",
							"subtask": false
						}
					}
				}
			},
			{
				"id": "48503",
				"type": {
					"id": "10003",
					"name": "Relates",
					"inward": "relates to",
					"outward": "relates to"
				},
				"outwardIssue": {
					"id": "149037",
					"key": "TIMOB-19063",
					"fields": {
						"summary": "Windows: default background color of sample apps",
						"status": {
							"description": "The issue is open and ready for the assignee to start work on it.",
							"name": "Open",
							"id": "1",
							"statusCategory": {
								"id": 2,
								"key": "new",
								"colorName": "blue-gray",
								"name": "To Do"
							}
						},
						"priority": {
							"name": "Medium",
							"id": "3"
						},
						"issuetype": {
							"id": "4",
							"description": "An improvement or enhancement to an existing feature or task.",
							"name": "Improvement",
							"subtask": false
						}
					}
				}
			},
			{
				"id": "48710",
				"type": {
					"id": "10003",
					"name": "Relates",
					"inward": "relates to",
					"outward": "relates to"
				},
				"outwardIssue": {
					"id": "150484",
					"key": "TIMOB-19368",
					"fields": {
						"summary": "Windows: backgroundImage for View subclasses",
						"status": {
							"description": "The issue is considered finished, the resolution is correct. Issues which are closed can be reopened.",
							"name": "Closed",
							"id": "6",
							"statusCategory": {
								"id": 3,
								"key": "done",
								"colorName": "green",
								"name": "Done"
							}
						},
						"priority": {
							"name": "Medium",
							"id": "3"
						},
						"issuetype": {
							"id": "4",
							"description": "An improvement or enhancement to an existing feature or task.",
							"name": "Improvement",
							"subtask": false
						}
					}
				}
			}
		],
		"assignee": {
			"name": "kiguchi",
			"key": "kota",
			"displayName": "Kota Iguchi",
			"active": false,
			"timeZone": "America/Los_Angeles"
		},
		"updated": "2017-03-16T22:32:04.000+0000",
		"status": {
			"description": "The issue is considered finished, the resolution is correct. Issues which are closed can be reopened.",
			"name": "Closed",
			"id": "6",
			"statusCategory": {
				"id": 3,
				"key": "done",
				"colorName": "green",
				"name": "Done"
			}
		},
		"components": [
			{
				"id": "12642",
				"name": "Windows",
				"description": "Windows authoring support"
			}
		],
		"description": "Import the Movies sample (alloy) by using the latest Appcelerator Studio 4.1.0 release, through the dashboard. Then verify that you are able to build it for Win Phone and Store (after adding windows to list of deploy targets in tiapp.xml).\r\n\r\nIf you run into any issues, please file additional tickets. If the sample needs to be updated in any way (like enabling capabilities), file a PR for the sample.\r\n\r\nhttps://github.com/appcelerator/movies",
		"attachment": [],
		"flagged": false,
		"summary": "Windows: Test Movies sample",
		"creator": {
			"name": "cwilliams",
			"key": "cwilliams",
			"displayName": "Christopher Williams",
			"active": true,
			"timeZone": "America/New_York"
		},
		"subtasks": [],
		"reporter": {
			"name": "cwilliams",
			"key": "cwilliams",
			"displayName": "Christopher Williams",
			"active": true,
			"timeZone": "America/New_York"
		},
		"environment": null,
		"closedSprints": [
			{
				"id": 484,
				"state": "closed",
				"name": "2015 Sprint 18 Windows",
				"startDate": "2015-08-30T04:01:00.000Z",
				"endDate": "2015-09-12T03:59:00.000Z",
				"completeDate": "2015-09-14T17:29:28.792Z",
				"originBoardId": 144
			}
		],
		"comment": {
			"comments": [
				{
					"id": "364510",
					"author": {
						"name": "ingo",
						"key": "ingo",
						"displayName": "Ingo Muschenetz",
						"active": true,
						"timeZone": "America/Los_Angeles"
					},
					"body": "Removing fix versions as this became two tickets for fixing actual issues.",
					"updateAuthor": {
						"name": "ingo",
						"key": "ingo",
						"displayName": "Ingo Muschenetz",
						"active": true,
						"timeZone": "America/Los_Angeles"
					},
					"created": "2015-09-21T18:49:20.000+0000",
					"updated": "2015-09-21T18:49:20.000+0000"
				},
				{
					"id": "413377",
					"author": {
						"name": "lmorris",
						"key": "lmorris",
						"displayName": "Lee Morris",
						"active": false,
						"timeZone": "America/Los_Angeles"
					},
					"body": "Closing ticket as fixed.",
					"updateAuthor": {
						"name": "lmorris",
						"key": "lmorris",
						"displayName": "Lee Morris",
						"active": false,
						"timeZone": "America/Los_Angeles"
					},
					"created": "2017-03-16T22:32:04.000+0000",
					"updated": "2017-03-16T22:32:04.000+0000"
				}
			],
			"maxResults": 2,
			"total": 2,
			"startAt": 0
		}
	}
}