{
	"id": "172677",
	"key": "MOD-2477",
	"fields": {
		"issuetype": {
			"id": "1",
			"description": "A problem which impairs or prevents the functions of the product.",
			"name": "Bug",
			"subtask": false
		},
		"project": {
			"id": "10034",
			"key": "MOD",
			"name": "Appcelerator Modules",
			"projectCategory": {
				"id": "10100",
				"description": "Titanium and related SDKs used in application development",
				"name": "Client"
			}
		},
		"fixVersions": [],
		"resolution": null,
		"resolutiondate": null,
		"created": "2018-11-28T13:19:08.000+0000",
		"priority": null,
		"labels": [
			"map",
			"module",
			"polygon"
		],
		"versions": [],
		"issuelinks": [],
		"assignee": null,
		"updated": "2018-11-30T23:43:19.000+0000",
		"status": {
			"description": "The issue is open and ready for the assignee to start work on it.",
			"name": "Open",
			"id": "1",
			"statusCategory": {
				"id": 2,
				"key": "new",
				"colorName": "blue-gray",
				"name": "To Do"
			}
		},
		"components": [
			{
				"id": "13700",
				"name": "Map"
			}
		],
		"description": "As per the docs there could be an _addPolygons_ method. \r\nThis is present and fully working on iOS but on Android we can only [add one polygon at time|https://github.com/appcelerator-modules/ti.map/blob/master/android/src/ti/map/ViewProxy.java#L722].",
		"attachment": [],
		"flagged": false,
		"summary": "Android - Module ti.map doesn't expose addPolygons method",
		"creator": {
			"name": "Andrea.Vitale",
			"key": "andrea.vitale",
			"displayName": "Andrea Vitale",
			"active": true,
			"timeZone": "Europe/Berlin"
		},
		"subtasks": [],
		"reporter": {
			"name": "Andrea.Vitale",
			"key": "andrea.vitale",
			"displayName": "Andrea Vitale",
			"active": true,
			"timeZone": "Europe/Berlin"
		},
		"environment": null,
		"comment": {
			"comments": [],
			"maxResults": 0,
			"total": 0,
			"startAt": 0
		}
	}
}