{
	"id": "131960",
	"key": "AC-903",
	"fields": {
		"issuetype": {
			"id": "1",
			"description": "A problem which impairs or prevents the functions of the product.",
			"name": "Bug",
			"subtask": false
		},
		"project": {
			"id": "12217",
			"key": "AC",
			"name": "Appcelerator - INBOX",
			"projectCategory": {
				"id": "10000",
				"description": "",
				"name": "Customer Service"
			}
		},
		"resolution": {
			"id": "5",
			"description": "All attempts at reproducing this issue failed, or not enough information was available to reproduce the issue. Reading the code produces no clues as to why this behavior would occur. If more information appears later, please reopen the issue.",
			"name": "Cannot Reproduce"
		},
		"resolutiondate": "2014-06-30T06:23:19.000+0000",
		"created": "2014-06-19T13:40:59.000+0000",
		"labels": [],
		"versions": [],
		"issuelinks": [],
		"assignee": {
			"name": "mpmiranda",
			"key": "mpmiranda",
			"displayName": "Mauro Parra-Miranda",
			"active": true,
			"timeZone": "America/Mexico_City"
		},
		"updated": "2016-03-08T07:37:12.000+0000",
		"status": {
			"description": "The issue is considered finished, the resolution is correct. Issues which are closed can be reopened.",
			"name": "Closed",
			"id": "6",
			"statusCategory": {
				"id": 3,
				"key": "done",
				"colorName": "green",
				"name": "Done"
			}
		},
		"components": [],
		"description": " Could not find Titanium module id=org.beuckman.tibeacons version=latest platform=iphone deploy-type=development",
		"attachment": [],
		"flagged": false,
		"summary": " Could not find Titanium module id=org.beuckman.tibeacons version=latest platform=iphone deploy-type=development",
		"creator": {
			"name": "srinivas",
			"key": "srinivas",
			"displayName": "srinivas",
			"active": true,
			"timeZone": "America/Los_Angeles"
		},
		"subtasks": [],
		"reporter": {
			"name": "srinivas",
			"key": "srinivas",
			"displayName": "srinivas",
			"active": true,
			"timeZone": "America/Los_Angeles"
		},
		"environment": "iOS ",
		"comment": {
			"comments": [
				{
					"id": "311241",
					"author": {
						"name": "sliang",
						"key": "sliang",
						"displayName": "Shuo Liang",
						"active": true,
						"timeZone": "Asia/Harbin"
					},
					"body": "Hi,\r\n\r\nI am afraid we need more information about your problem. Maybe a test case is helpful.\r\n\r\nRegards,\r\nShuo",
					"updateAuthor": {
						"name": "sliang",
						"key": "sliang",
						"displayName": "Shuo Liang",
						"active": true,
						"timeZone": "Asia/Harbin"
					},
					"created": "2014-06-27T08:00:37.000+0000",
					"updated": "2014-06-27T08:00:37.000+0000"
				},
				{
					"id": "311552",
					"author": {
						"name": "mpmiranda",
						"key": "mpmiranda",
						"displayName": "Mauro Parra-Miranda",
						"active": true,
						"timeZone": "America/Mexico_City"
					},
					"body": "Hello!\r\n\r\nPlease provide a testcase for this issue, that shows the issue. \r\n\r\nPlease read the guide to add a module into your project, that might help. \r\n\r\nhttp://docs.appcelerator.com/titanium/3.0/#!/guide/Using_a_Module\r\n\r\nBest Regards, ",
					"updateAuthor": {
						"name": "mpmiranda",
						"key": "mpmiranda",
						"displayName": "Mauro Parra-Miranda",
						"active": true,
						"timeZone": "America/Mexico_City"
					},
					"created": "2014-06-30T06:23:20.000+0000",
					"updated": "2014-06-30T06:23:20.000+0000"
				}
			],
			"maxResults": 2,
			"total": 2,
			"startAt": 0
		}
	}
}