{
	"id": "153721",
	"key": "TIMOB-20125",
	"fields": {
		"issuetype": {
			"id": "4",
			"description": "An improvement or enhancement to an existing feature or task.",
			"name": "Improvement",
			"subtask": false
		},
		"project": {
			"id": "10153",
			"key": "TIMOB",
			"name": "Titanium SDK/CLI",
			"projectCategory": {
				"id": "10100",
				"description": "Titanium and related SDKs used in application development",
				"name": "Client"
			}
		},
		"fixVersions": [],
		"resolution": null,
		"resolutiondate": null,
		"created": "2015-12-09T07:07:44.000+0000",
		"priority": {
			"name": "Low",
			"id": "4"
		},
		"labels": [
			"button"
		],
		"versions": [],
		"issuelinks": [
			{
				"id": "50077",
				"type": {
					"id": "10003",
					"name": "Relates",
					"inward": "relates to",
					"outward": "relates to"
				},
				"inwardIssue": {
					"id": "149882",
					"key": "TIMOB-19250",
					"fields": {
						"summary": "SDK: Improvement from customer's custom SDK commit.",
						"status": {
							"description": "A resolution has been taken, and it is awaiting verification by reporter. From here issues are either reopened, or are closed.",
							"name": "Resolved",
							"id": "5",
							"statusCategory": {
								"id": 3,
								"key": "done",
								"colorName": "green",
								"name": "Done"
							}
						},
						"priority": {
							"name": "High",
							"id": "2"
						},
						"issuetype": {
							"id": "4",
							"description": "An improvement or enhancement to an existing feature or task.",
							"name": "Improvement",
							"subtask": false
						}
					}
				}
			}
		],
		"assignee": null,
		"updated": "2018-02-28T19:55:58.000+0000",
		"status": {
			"description": "The issue is open and ready for the assignee to start work on it.",
			"name": "Open",
			"id": "1",
			"statusCategory": {
				"id": 2,
				"key": "new",
				"colorName": "blue-gray",
				"name": "To Do"
			}
		},
		"components": [
			{
				"id": "10202",
				"name": "Android",
				"description": "Android Platform"
			}
		],
		"description": "Add property to choose the selectedColor of button on android.",
		"attachment": [],
		"flagged": false,
		"summary": "Android: Support selectedColor for UI button",
		"creator": {
			"name": "cng",
			"key": "cng",
			"displayName": "Chee Kiat Ng",
			"active": false,
			"timeZone": "America/Los_Angeles"
		},
		"subtasks": [],
		"reporter": {
			"name": "cng",
			"key": "cng",
			"displayName": "Chee Kiat Ng",
			"active": false,
			"timeZone": "America/Los_Angeles"
		},
		"environment": null,
		"comment": {
			"comments": [],
			"maxResults": 0,
			"total": 0,
			"startAt": 0
		}
	}
}