{
	"id": "154644",
	"key": "TIMOB-20307",
	"fields": {
		"issuetype": {
			"id": "4",
			"description": "An improvement or enhancement to an existing feature or task.",
			"name": "Improvement",
			"subtask": false
		},
		"project": {
			"id": "10153",
			"key": "TIMOB",
			"name": "Titanium SDK/CLI",
			"projectCategory": {
				"id": "10100",
				"description": "Titanium and related SDKs used in application development",
				"name": "Client"
			}
		},
		"fixVersions": [],
		"resolution": {
			"id": "3",
			"description": "The problem is a duplicate of an existing issue.",
			"name": "Duplicate"
		},
		"resolutiondate": "2016-02-02T21:47:34.000+0000",
		"created": "2016-02-02T15:47:20.000+0000",
		"priority": {
			"name": "None",
			"id": "6"
		},
		"labels": [],
		"versions": [],
		"issuelinks": [
			{
				"id": "50405",
				"type": {
					"id": "10002",
					"name": "Duplicate",
					"inward": "is duplicated by",
					"outward": "duplicates"
				},
				"outwardIssue": {
					"id": "144631",
					"key": "TIMOB-18567",
					"fields": {
						"summary": "Windows: Implement Ti.Map module",
						"status": {
							"description": "The issue is considered finished, the resolution is correct. Issues which are closed can be reopened.",
							"name": "Closed",
							"id": "6",
							"statusCategory": {
								"id": 3,
								"key": "done",
								"colorName": "green",
								"name": "Done"
							}
						},
						"priority": {
							"name": "High",
							"id": "2"
						},
						"issuetype": {
							"id": "2",
							"description": "A new feature of the product, which has yet to be developed.",
							"name": "New Feature",
							"subtask": false
						}
					}
				}
			},
			{
				"id": "50406",
				"type": {
					"id": "10002",
					"name": "Duplicate",
					"inward": "is duplicated by",
					"outward": "duplicates"
				},
				"outwardIssue": {
					"id": "144632",
					"key": "TIMOB-18568",
					"fields": {
						"summary": "Windows: Implement Ti.Map.Annotation proxy",
						"status": {
							"description": "The issue is considered finished, the resolution is correct. Issues which are closed can be reopened.",
							"name": "Closed",
							"id": "6",
							"statusCategory": {
								"id": 3,
								"key": "done",
								"colorName": "green",
								"name": "Done"
							}
						},
						"priority": {
							"name": "High",
							"id": "2"
						},
						"issuetype": {
							"id": "2",
							"description": "A new feature of the product, which has yet to be developed.",
							"name": "New Feature",
							"subtask": false
						}
					}
				}
			},
			{
				"id": "50407",
				"type": {
					"id": "10002",
					"name": "Duplicate",
					"inward": "is duplicated by",
					"outward": "duplicates"
				},
				"outwardIssue": {
					"id": "144633",
					"key": "TIMOB-18569",
					"fields": {
						"summary": "Windows: Implement Ti.Map.View proxy",
						"status": {
							"description": "The issue is considered finished, the resolution is correct. Issues which are closed can be reopened.",
							"name": "Closed",
							"id": "6",
							"statusCategory": {
								"id": 3,
								"key": "done",
								"colorName": "green",
								"name": "Done"
							}
						},
						"priority": {
							"name": "High",
							"id": "2"
						},
						"issuetype": {
							"id": "2",
							"description": "A new feature of the product, which has yet to be developed.",
							"name": "New Feature",
							"subtask": false
						}
					}
				}
			},
			{
				"id": "50403",
				"type": {
					"id": "10003",
					"name": "Relates",
					"inward": "relates to",
					"outward": "relates to"
				},
				"outwardIssue": {
					"id": "154501",
					"key": "TIDOC-2430",
					"fields": {
						"summary": "Windows: Lots of API undocumented",
						"status": {
							"description": "The issue is considered finished, the resolution is correct. Issues which are closed can be reopened.",
							"name": "Closed",
							"id": "6",
							"statusCategory": {
								"id": 3,
								"key": "done",
								"colorName": "green",
								"name": "Done"
							}
						},
						"priority": {
							"name": "None",
							"id": "6"
						},
						"issuetype": {
							"id": "1",
							"description": "A problem which impairs or prevents the functions of the product.",
							"name": "Bug",
							"subtask": false
						}
					}
				}
			}
		],
		"assignee": {
			"name": "cwilliams",
			"key": "cwilliams",
			"displayName": "Christopher Williams",
			"active": true,
			"timeZone": "America/New_York"
		},
		"updated": "2017-03-20T22:06:30.000+0000",
		"status": {
			"description": "The issue is considered finished, the resolution is correct. Issues which are closed can be reopened.",
			"name": "Closed",
			"id": "6",
			"statusCategory": {
				"id": 3,
				"key": "done",
				"colorName": "green",
				"name": "Done"
			}
		},
		"components": [
			{
				"id": "12642",
				"name": "Windows",
				"description": "Windows authoring support"
			}
		],
		"description": "Add support for Map Module for Windows Phone\r\n\r\nhttp://docs.appcelerator.com/platform/latest/#!/api/Modules.Map",
		"attachment": [],
		"flagged": false,
		"summary": "Windows: Add support for Map Module",
		"creator": {
			"name": "lbrenman",
			"key": "lbrenman",
			"displayName": "Leor Brenman",
			"active": true,
			"timeZone": "America/Havana"
		},
		"subtasks": [],
		"reporter": {
			"name": "lbrenman",
			"key": "lbrenman",
			"displayName": "Leor Brenman",
			"active": true,
			"timeZone": "America/Havana"
		},
		"environment": null,
		"comment": {
			"comments": [
				{
					"id": "375771",
					"author": {
						"name": "cwilliams",
						"key": "cwilliams",
						"displayName": "Christopher Williams",
						"active": true,
						"timeZone": "America/New_York"
					},
					"body": "We have the ti.map module implemented in the core of the SDK for Windows. So we do actually have support for http://docs.appcelerator.com/platform/latest/#!/api/Modules.Map",
					"updateAuthor": {
						"name": "cwilliams",
						"key": "cwilliams",
						"displayName": "Christopher Williams",
						"active": true,
						"timeZone": "America/New_York"
					},
					"created": "2016-02-02T21:42:57.000+0000",
					"updated": "2016-02-02T21:42:57.000+0000"
				},
				{
					"id": "375773",
					"author": {
						"name": "cwilliams",
						"key": "cwilliams",
						"displayName": "Christopher Williams",
						"active": true,
						"timeZone": "America/New_York"
					},
					"body": "Marking as dupe since we already do have support for this, it's a matter of the docs not showing that we do (see TIDOC-2430)",
					"updateAuthor": {
						"name": "cwilliams",
						"key": "cwilliams",
						"displayName": "Christopher Williams",
						"active": true,
						"timeZone": "America/New_York"
					},
					"created": "2016-02-02T21:47:35.000+0000",
					"updated": "2016-02-02T21:47:35.000+0000"
				},
				{
					"id": "414043",
					"author": {
						"name": "lmorris",
						"key": "lmorris",
						"displayName": "Lee Morris",
						"active": false,
						"timeZone": "America/Los_Angeles"
					},
					"body": "Closing ticket as duplicate.",
					"updateAuthor": {
						"name": "lmorris",
						"key": "lmorris",
						"displayName": "Lee Morris",
						"active": false,
						"timeZone": "America/Los_Angeles"
					},
					"created": "2017-03-20T22:06:30.000+0000",
					"updated": "2017-03-20T22:06:30.000+0000"
				}
			],
			"maxResults": 3,
			"total": 3,
			"startAt": 0
		}
	}
}